atsphinx/revealjs_rtd/__init__.py
atsphinx/revealjs_rtd/static/atsphinx-revealjs-rtd/plugin.js
atsphinx/revealjs_rtd/static/atsphinx-revealjs-rtd/rtd.esm.js
atsphinx/revealjs_rtd/static/atsphinx-revealjs-rtd/rtd.js
atsphinx_revealjs_rtd-0.2.0.dist-info/METADATA
atsphinx_revealjs_rtd-0.2.0.dist-info/WHEEL
atsphinx_revealjs_rtd-0.2.0.dist-info/licenses/LICENSE
atsphinx_revealjs_rtd-0.2.0.dist-info/RECORD
